{
  "phase": "FAZ_3_10_8_4_EXPORT_SMOKE",
  "runtime": "export_smoke_runtime",
  "runtime_enabled": true,
  "require_all_modules": true,
  "require_eta_format": true,
  "require_logo_format": true,
  "require_mikro_format": true,
  "require_zirve_format": true,
  "require_format_matrix": true,
  "require_adapter_tests": true,
  "require_tenant_guard": true,
  "require_correlation_guard": true,
  "require_idempotency_guard": true,
  "require_smoke_hash": true,
  "minimum_pass_count": 70,
  "required_modules": [
    "ETA_REAL_FORMAT_GENERATION",
    "LOGO_REAL_FORMAT_GENERATION",
    "MIKRO_REAL_FORMAT_GENERATION",
    "ZIRVE_REAL_FORMAT_GENERATION",
    "FORMAT_VALIDATION_MATRIX_RUNTIME",
    "EXPORT_ADAPTER_TESTS"
  ],
  "covered_gates": [
    "FAZ_3_10_4_4_ETA_REAL_FORMAT_GENERATION",
    "FAZ_3_10_4_1_LOGO_REAL_FORMAT_GENERATION",
    "FAZ_3_10_4_2_MIKRO_REAL_FORMAT_GENERATION",
    "FAZ_3_10_4_3_ZIRVE_REAL_FORMAT_GENERATION",
    "FAZ_3_10_4_5_FORMAT_VALIDATION_MATRIX_RUNTIME",
    "FAZ_3_10_4_6_EXPORT_ADAPTER_TESTS"
  ],
  "live_policy": {
    "production_approved": false,
    "real_delivery_status": "CLOSED",
    "real_external_provider_calls_allowed": false,
    "export_smoke_is_readiness_only": true
  },
  "guard_policy": {
    "tenant_id_required": true,
    "correlation_id_required": true,
    "request_id_required": true,
    "idempotency_key_required": true,
    "smoke_id_required": true,
    "requested_at_required": true,
    "minimum_pass_count_required": true,
    "smoke_hash_required": true
  },
  "previous_gate": "FAZ_3_10_8_2_TAX_SMOKE",
  "next_gate": "FAZ_3_10_8_5_PAYMENT_SMOKE"
}
