{
  "phase": "FAZ_3_12_6_PORTAL_AUDIT_HISTORY",
  "screen": "portal_audit_history",
  "screen_enabled": true,
  "route": "/faz3/accountant-portal/audit-history/",
  "static_file": "web/faz3/accountant-portal/audit-history/index.html",
  "scope": {
    "portal_audit_history_visibility": true,
    "append_only_audit_visibility": true,
    "company_switch_event_visibility": true,
    "permission_decision_event_visibility": true,
    "export_request_event_visibility": true,
    "subscription_validate_event_visibility": true,
    "access_decision_event_visibility": true,
    "actor_visibility": true,
    "tenant_scope_visibility": true,
    "firm_scope_visibility": true,
    "correlation_visibility": true,
    "request_id_visibility": true,
    "idempotency_key_visibility": true,
    "ip_hash_visibility": true,
    "user_agent_hash_visibility": true,
    "before_after_state_hash_visibility": true,
    "event_hash_visibility": true,
    "scope_hash_visibility": true,
    "chain_hash_visibility": true,
    "evidence_hash_visibility": true,
    "evidence_file_visibility": true,
    "hash_timeline_visibility": true
  },
  "guard_policy": {
    "tenant_indicator_required": true,
    "accountant_indicator_required": true,
    "firm_indicator_required": true,
    "audit_id_required": true,
    "event_type_required": true,
    "firm_id_required": true,
    "tenant_id_required": true,
    "accountant_id_required": true,
    "actor_id_required": true,
    "actor_role_required": true,
    "decision_required": true,
    "period_required": true,
    "action_required": true,
    "source_screen_required": true,
    "target_resource_required": true,
    "correlation_id_required": true,
    "request_id_required": true,
    "idempotency_key_required": true,
    "ip_hash_required": true,
    "user_agent_hash_required": true,
    "before_state_hash_required": true,
    "after_state_hash_required": true,
    "event_hash_required": true,
    "scope_hash_required": true,
    "chain_hash_required": true,
    "evidence_hash_required": true,
    "evidence_file_required": true,
    "created_at_required": true
  },
  "event_type_coverage": {
    "event_company_switch": true,
    "event_permission_decision": true,
    "event_export_request": true,
    "event_subscription_validate": true,
    "event_access_decision": true
  },
  "decision_coverage": {
    "decision_allow": true,
    "decision_review_required": true,
    "decision_deny": true,
    "decision_read_only": true
  },
  "source_screen_coverage": {
    "company_switcher": true,
    "company_permission_screen": true,
    "accountant_export_workspace": true,
    "subscription_status_view": true
  },
  "live_policy": {
    "production_approved": false,
    "append_only_audit_required": true,
    "audit_delete_allowed": false,
    "audit_mutation_allowed": false,
    "cross_tenant_audit_read_allowed": false,
    "evidence_hash_required": true,
    "actor_required": true,
    "correlation_required": true,
    "ui_actions_are_detail_verify_export_evidence_only": true
  },
  "covered_backend_gates": [
    "FAZ_3_12_2_COMPANY_SWITCHER",
    "FAZ_3_12_3_COMPANY_BASED_PERMISSION_SCREEN",
    "FAZ_3_12_4_ACCOUNTANT_EXPORT_WORKSPACE",
    "FAZ_3_12_5_SUBSCRIPTION_STATUS_VIEW"
  ],
  "previous_gate": "FAZ_3_12_5_SUBSCRIPTION_STATUS_VIEW",
  "next_gate": "FAZ_3_12_7_ACCOUNTANT_PORTAL_TESTS"
}
